setup.py
snfilter/__init__.py
snfilter/scripts.py
snfilter.egg-info/PKG-INFO
snfilter.egg-info/SOURCES.txt
snfilter.egg-info/dependency_links.txt
snfilter.egg-info/entry_points.txt
snfilter.egg-info/not-zip-safe
snfilter.egg-info/requires.txt
snfilter.egg-info/top_level.txt