Metadata-Version: 1.0
Name: snfilter
Version: 0.2
Summary: Spotter Network Filtered Feeds
Home-page: https://github.com/stephanellis/snfilter
Author: Stephan M Ellis
Author-email: stephan.ellis@gmail.com
License: MIT
Platform: UNKNOWN
